<?xml version="1.0" encoding="UTF-8"?>

<server>

    <!-- OpenSPCoop2 -->
    <mbean code="org.jboss.jms.server.destination.QueueService"
         name="jboss.messaging.destination:service=Queue,name=toImbustamento"
      xmbean-dd="xmdesc/Queue-xmbean.xml">
      <depends optional-attribute-name="ServerPeer">jboss.messaging:service=ServerPeer</depends>
      <depends>jboss.messaging:service=PostOffice</depends>
      <attribute name="RedeliveryDelay">120000</attribute>
         <!--<attribute name="MaxDeliveryAttempts">200</attribute>-->
    </mbean>
    <mbean code="org.jboss.jms.server.destination.QueueService"
         name="jboss.messaging.destination:service=Queue,name=toInoltroBuste"
      xmbean-dd="xmdesc/Queue-xmbean.xml">
      <depends optional-attribute-name="ServerPeer">jboss.messaging:service=ServerPeer</depends>
      <depends>jboss.messaging:service=PostOffice</depends>
      <attribute name="RedeliveryDelay">60000</attribute>
         <!--<attribute name="MaxDeliveryAttempts">200</attribute>-->
    </mbean>
    <mbean code="org.jboss.jms.server.destination.QueueService"
         name="jboss.messaging.destination:service=Queue,name=toInoltroRisposte"
      xmbean-dd="xmdesc/Queue-xmbean.xml">
      <depends optional-attribute-name="ServerPeer">jboss.messaging:service=ServerPeer</depends>
      <depends>jboss.messaging:service=PostOffice</depends>
      <attribute name="RedeliveryDelay">60000</attribute>
         <!--<attribute name="MaxDeliveryAttempts">200</attribute>-->
    </mbean>
    <mbean code="org.jboss.jms.server.destination.QueueService"
         name="jboss.messaging.destination:service=Queue,name=toSbustamento"
      xmbean-dd="xmdesc/Queue-xmbean.xml">
      <depends optional-attribute-name="ServerPeer">jboss.messaging:service=ServerPeer</depends>
      <depends>jboss.messaging:service=PostOffice</depends>
      <attribute name="RedeliveryDelay">120000</attribute>
         <!--<attribute name="MaxDeliveryAttempts">200</attribute>-->
    </mbean>
    <mbean code="org.jboss.jms.server.destination.QueueService"
         name="jboss.messaging.destination:service=Queue,name=toConsegnaContenutiApplicativi"
      xmbean-dd="xmdesc/Queue-xmbean.xml">
      <depends optional-attribute-name="ServerPeer">jboss.messaging:service=ServerPeer</depends>
      <depends>jboss.messaging:service=PostOffice</depends>
      <attribute name="RedeliveryDelay">60000</attribute>
         <!--<attribute name="MaxDeliveryAttempts">200</attribute>-->
    </mbean>
    <mbean code="org.jboss.jms.server.destination.QueueService"
         name="jboss.messaging.destination:service=Queue,name=toImbustamentoRisposte"
      xmbean-dd="xmdesc/Queue-xmbean.xml">
      <depends optional-attribute-name="ServerPeer">jboss.messaging:service=ServerPeer</depends>
      <depends>jboss.messaging:service=PostOffice</depends>
      <attribute name="RedeliveryDelay">120000</attribute>
         <!--<attribute name="MaxDeliveryAttempts">200</attribute>-->
    </mbean>
    <mbean code="org.jboss.jms.server.destination.QueueService"
         name="jboss.messaging.destination:service=Queue,name=toSbustamentoRisposte"
      xmbean-dd="xmdesc/Queue-xmbean.xml">
      <depends optional-attribute-name="ServerPeer">jboss.messaging:service=ServerPeer</depends>
      <depends>jboss.messaging:service=PostOffice</depends>
      <attribute name="RedeliveryDelay">120000</attribute>
         <!--<attribute name="MaxDeliveryAttempts">200</attribute>-->
    </mbean>
    <mbean code="org.jboss.jms.server.destination.QueueService"
         name="jboss.messaging.destination:service=Queue,name=toRicezioneBuste"
      xmbean-dd="xmdesc/Queue-xmbean.xml">
      <depends optional-attribute-name="ServerPeer">jboss.messaging:service=ServerPeer</depends>
      <depends>jboss.messaging:service=PostOffice</depends>
      <attribute name="RedeliveryDelay">120000</attribute>
         <!--<attribute name="MaxDeliveryAttempts">200</attribute>-->
    </mbean>
    <mbean code="org.jboss.jms.server.destination.QueueService"
         name="jboss.messaging.destination:service=Queue,name=toRicezioneContenutiApplicativi"
      xmbean-dd="xmdesc/Queue-xmbean.xml">
      <depends optional-attribute-name="ServerPeer">jboss.messaging:service=ServerPeer</depends>
      <depends>jboss.messaging:service=PostOffice</depends>
      <attribute name="RedeliveryDelay">120000</attribute>
         <!--<attribute name="MaxDeliveryAttempts">200</attribute>-->
    </mbean>
    <!-- OpenSPCoop2 -->

</server>
